MANIFEST.in
setup.py
django_dirtyfield.egg-info/PKG-INFO
django_dirtyfield.egg-info/SOURCES.txt
django_dirtyfield.egg-info/dependency_links.txt
django_dirtyfield.egg-info/requires.txt
django_dirtyfield.egg-info/top_level.txt
djangodirtyfield/__init__.py
djangodirtyfield/apps.py
djangodirtyfield/mixin.py