Metadata-Version: 1.0
Name: django-dirtyfield
Version: 1.0
Summary: Track changed data in Django Models
Home-page: http://github.com/futurice/django-dirtyfield
Author: Jussi Vaihia
Author-email: jussi.vaihia@futurice.com
License: BSD
Keywords: django model dirty field
Platform: UNKNOWN
